.coveragerc
AUTHORS.rst
CHANGES.rst
LICENSE.txt
README.rst
requirements.txt
setup.cfg
setup.py
test-requirements.txt
.github/workflows/pythonpackage.yml
.github/workflows/pythonpush.yml
deep_keyphrase/__init__.py
deep_keyphrase/base_predictor.py
deep_keyphrase/base_trainer.py
deep_keyphrase/dataloader.py
deep_keyphrase/evaluation.py
deep_keyphrase/predict_runner.py
deep_keyphrase.egg-info/PKG-INFO
deep_keyphrase.egg-info/SOURCES.txt
deep_keyphrase.egg-info/dependency_links.txt
deep_keyphrase.egg-info/not-zip-safe
deep_keyphrase.egg-info/requires.txt
deep_keyphrase.egg-info/top_level.txt
deep_keyphrase/copy_cnn/__init__.py
deep_keyphrase/copy_cnn/beam_search.py
deep_keyphrase/copy_cnn/model.py
deep_keyphrase/copy_cnn/predict.py
deep_keyphrase/copy_cnn/train.py
deep_keyphrase/copy_rnn/__init__.py
deep_keyphrase/copy_rnn/beam_search.py
deep_keyphrase/copy_rnn/model.py
deep_keyphrase/copy_rnn/model_tf.py
deep_keyphrase/copy_rnn/predict.py
deep_keyphrase/copy_rnn/predict_tf.py
deep_keyphrase/copy_rnn/train.py
deep_keyphrase/copy_rnn/train_tf.py
deep_keyphrase/copy_transformer/__init__.py
deep_keyphrase/copy_transformer/beam_search.py
deep_keyphrase/copy_transformer/model.py
deep_keyphrase/copy_transformer/predict.py
deep_keyphrase/copy_transformer/train.py
deep_keyphrase/copy_transformer/transformer.py
deep_keyphrase/data_process/__init__.py
deep_keyphrase/data_process/preprocess.py
deep_keyphrase/utils/__init__.py
deep_keyphrase/utils/constants.py
deep_keyphrase/utils/tokenizer.py
deep_keyphrase/utils/vocab_loader.py
docs/Makefile
docs/authors.rst
docs/changes.rst
docs/conf.py
docs/index.rst
docs/license.rst
docs/_static/.gitignore
scripts/predict_kp20k.sh
scripts/prepare_kp20k.sh
scripts/train_copyrnn_kp20k.sh
tests/test_utils/__init__.py
tests/test_utils/test_tokenizer.py