Metadata-Version: 2.1
Name: deep-keyphrase
Version: 0.0.8
Summary: Add a short description here!
Home-page: https://github.com/supercoderhawk/deep-keyphrase
Author: xiayubin
Author-email: supercoderhawk@gmail.com
License: MIT
Platform: UNKNOWN
Classifier: Development Status :: 4 - Beta
Classifier: Programming Language :: Python
Provides-Extra: test
